{
  "input_file_count": 9,
  "input_line_count": 3039,
  "parsed_edge_count": 3039,
  "merged_unique_edge_count": 2863,
  "duplicate_edge_count": 176,
  "malformed_line_count": 0,
  "self_edge_count": 0,
  "files": [
    {
      "path": "knowledge-map-gen/map-store/two_phase/phase1_raw.txt",
      "line_count": 156,
      "parsed_edge_count": 156,
      "kept_edge_count": 156,
      "duplicate_edge_count": 0,
      "malformed_line_count": 0,
      "self_edge_count": 0
    },
    {
      "path": "knowledge-map-gen/map-store/two_phase/phase2/phase2_raw_01_algorithms.txt",
      "line_count": 325,
      "parsed_edge_count": 325,
      "kept_edge_count": 318,
      "duplicate_edge_count": 7,
      "malformed_line_count": 0,
      "self_edge_count": 0
    },
    {
      "path": "knowledge-map-gen/map-store/two_phase/phase2/phase2_raw_02_data_structures.txt",
      "line_count": 395,
      "parsed_edge_count": 395,
      "kept_edge_count": 384,
      "duplicate_edge_count": 11,
      "malformed_line_count": 0,
      "self_edge_count": 0
    },
    {
      "path": "knowledge-map-gen/map-store/two_phase/phase2/phase2_raw_03_operating_systems.txt",
      "line_count": 437,
      "parsed_edge_count": 437,
      "kept_edge_count": 432,
      "duplicate_edge_count": 5,
      "malformed_line_count": 0,
      "self_edge_count": 0
    },
    {
      "path": "knowledge-map-gen/map-store/two_phase/phase2/phase2_raw_04_computer_networks.txt",
      "line_count": 323,
      "parsed_edge_count": 323,
      "kept_edge_count": 316,
      "duplicate_edge_count": 7,
      "malformed_line_count": 0,
      "self_edge_count": 0
    },
    {
      "path": "knowledge-map-gen/map-store/two_phase/phase2/phase2_raw_05_databases.txt",
      "line_count": 369,
      "parsed_edge_count": 369,
      "kept_edge_count": 325,
      "duplicate_edge_count": 44,
      "malformed_line_count": 0,
      "self_edge_count": 0
    },
    {
      "path": "knowledge-map-gen/map-store/two_phase/phase2/phase2_raw_06_distributed_systems.txt",
      "line_count": 428,
      "parsed_edge_count": 428,
      "kept_edge_count": 415,
      "duplicate_edge_count": 13,
      "malformed_line_count": 0,
      "self_edge_count": 0
    },
    {
      "path": "knowledge-map-gen/map-store/two_phase/phase2/phase2_raw_07_software_engineering.txt",
      "line_count": 325,
      "parsed_edge_count": 325,
      "kept_edge_count": 267,
      "duplicate_edge_count": 58,
      "malformed_line_count": 0,
      "self_edge_count": 0
    },
    {
      "path": "knowledge-map-gen/map-store/two_phase/phase2/phase2_raw_08_machine_learning.txt",
      "line_count": 281,
      "parsed_edge_count": 281,
      "kept_edge_count": 250,
      "duplicate_edge_count": 31,
      "malformed_line_count": 0,
      "self_edge_count": 0
    }
  ]
}